odoo/addons/sale_purchase_procurement_group_by_line/README.rst
odoo/addons/sale_purchase_procurement_group_by_line/__init__.py
odoo/addons/sale_purchase_procurement_group_by_line/__manifest__.py
odoo/addons/sale_purchase_procurement_group_by_line/i18n/sale_purchase_procurement_group_by_line.pot
odoo/addons/sale_purchase_procurement_group_by_line/models/__init__.py
odoo/addons/sale_purchase_procurement_group_by_line/models/sale_order.py
odoo/addons/sale_purchase_procurement_group_by_line/readme/CONTRIBUTORS.rst
odoo/addons/sale_purchase_procurement_group_by_line/readme/DESCRIPTION.rst
odoo/addons/sale_purchase_procurement_group_by_line/static/description/icon.png
odoo/addons/sale_purchase_procurement_group_by_line/static/description/index.html
odoo_addon_sale_purchase_procurement_group_by_line-15.0.1.0.0.2.dist-info/METADATA
odoo_addon_sale_purchase_procurement_group_by_line-15.0.1.0.0.2.dist-info/WHEEL
odoo_addon_sale_purchase_procurement_group_by_line-15.0.1.0.0.2.dist-info/top_level.txt
odoo_addon_sale_purchase_procurement_group_by_line-15.0.1.0.0.2.dist-info/RECORD
