Metadata-Version: 2.1
Name: odoo-addon-sale-purchase-procurement-group-by-line
Version: 15.0.1.0.0.2
Summary: Glue module between 'MTO Sale <-> Purchase' and 'Sale Procurement Group by Line'
Home-page: https://github.com/OCA/sale-workflow
Author: Camptocamp, Odoo Community Association (OCA)
Author-email: support@odoo-community.org
License: AGPL-3
Platform: UNKNOWN
Classifier: Programming Language :: Python
Classifier: Framework :: Odoo
Classifier: Framework :: Odoo :: 15.0
Classifier: License :: OSI Approved :: GNU Affero General Public License v3
Requires-Python: >=3.8
Requires-Dist: odoo-addon-sale-procurement-group-by-line <15.1dev,>=15.0dev
Requires-Dist: odoo <15.1dev,>=15.0a
